{
  "generated_at": "2026-01-29T00:51:20.106101+08:00",
  "total_titles_processed": 315,
  "failed_sources": [],
  "trends": [
    {
      "keyword_group": "美元",
      "match_count": 14,
      "titles": [
        {
          "title": "科技巨头财报前标普五连阳，美元重挫创四年新低，黄金又新高，原油拉升，期银跳水",
          "url": "https://wallstreetcn.com/articles/3764253",
          "source": "华尔街见闻",
          "ranks": [
            1
          ],
          "is_new": false,
          "appearance_count": 1,
          "time_info": "00时51分"
        },
        {
          "title": "高盛测算，在MSCI评估市场准入情况后，印尼股市在良性情景下可能面临22亿美元的被动资金流出，在极端情景下这一数字可能高达78亿美元。",
          "url": "https://flash.jin10.com/detail/20260129003312980800",
          "source": "金十数据",
          "ranks": [
            1
          ],
          "is_new": false,
          "appearance_count": 1,
          "time_info": "00时51分"
        },
        {
          "title": "美联储决议前，强劲财报提振科技股，标普500突破7000点创新高，阿斯麦转跌，美元止跌，黄金5300，银、铜、铝集体上涨",
          "url": "https://wallstreetcn.com/articles/3764338",
          "source": "华尔街见闻",
          "ranks": [
            2
          ],
          "is_new": false,
          "appearance_count": 1,
          "time_info": "00时51分"
        },
        {
          "title": "美元跌至四年低谷，特朗普“火上浇油”：不担心，美元表现出色，能找到合理水平",
          "url": "https://wallstreetcn.com/articles/3764299",
          "source": "华尔街见闻",
          "ranks": [
            4
          ],
          "is_new": false,
          "appearance_count": 1,
          "time_info": "00时51分"
        },
        {
          "title": "美国总统特朗普在特朗普账户活动上发表讲话时称赞戴尔电脑，此前戴尔夫妇为“特朗普账户”豪捐62.5亿美元 。",
          "url": "https://flash.jin10.com/detail/20260129002349346800",
          "source": "金十数据",
          "ranks": [
            6
          ],
          "is_new": false,
          "appearance_count": 1,
          "time_info": "00时51分"
        },
        {
          "title": "未来几周看涨到150美元！花旗高喊白银是“打了兴奋剂的黄金”，中国主导、印度跟买，但全球ETF净流出",
          "url": "https://wallstreetcn.com/articles/3764316",
          "source": "华尔街见闻",
          "ranks": [
            7
          ],
          "is_new": false,
          "appearance_count": 1,
          "time_info": "00时51分"
        },
        {
          "title": "美元走软叠加乙醇政策预期 美农产品市场迎来看涨转机",
          "url": "https://flash.jin10.com/detail/20260129001304512800",
          "source": "金十数据",
          "ranks": [
            7
          ],
          "is_new": false,
          "appearance_count": 1,
          "time_info": "00时51分"
        },
        {
          "title": "高盛外汇交易员：下跌才刚刚开始，美元迎来新一轮贬值",
          "url": "https://wallstreetcn.com/articles/3764318",
          "source": "华尔街见闻",
          "ranks": [
            9
          ],
          "is_new": false,
          "appearance_count": 1,
          "time_info": "00时51分"
        },
        {
          "title": "资管机构：预计美元今年将下探最近十一年低位，跌势可能至少会持续至特朗普任期届满",
          "url": "https://wallstreetcn.com/livenews/3045703",
          "source": "华尔街见闻-快讯",
          "ranks": [
            9
          ],
          "is_new": false,
          "appearance_count": 1,
          "time_info": "00时51分"
        },
        {
          "title": "黄金突破 5300 美元关口，国内金饰克价突破 1610 元，黄金还能涨多久？",
          "url": "https://www.zhihu.com/question/1999138722730500772",
          "source": "知乎",
          "ranks": [
            11
          ],
          "is_new": false,
          "appearance_count": 1,
          "time_info": "00时51分"
        },
        {
          "title": "行业咨询公司CRU Group预计，2026年全球铜实际均价将为5.12美元/磅。 关键驱动因素包括中国和全球对精炼铜的消费需求的增长。 预计全球2026年铜消费将增长3%左右。",
          "url": "https://wallstreetcn.com/livenews/3045690",
          "source": "华尔街见闻-快讯",
          "ranks": [
            19
          ],
          "is_new": false,
          "appearance_count": 1,
          "time_info": "00时51分"
        },
        {
          "title": "加拿大央行行长麦克勒姆：美元的避风港角色已经削弱。",
          "url": "https://flash.jin10.com/detail/20260128235723824800",
          "source": "金十数据",
          "ranks": [
            21
          ],
          "is_new": false,
          "appearance_count": 1,
          "time_info": "00时51分"
        },
        {
          "title": "加拿大央行行长麦克勒姆：近期美元走软在很大程度上是由地缘政治事件推动的。",
          "url": "https://flash.jin10.com/detail/20260128235610702800",
          "source": "金十数据",
          "ranks": [
            24
          ],
          "is_new": false,
          "appearance_count": 1,
          "time_info": "00时51分"
        },
        {
          "title": "美元兑日元涨幅扩大至1%，美国财长贝森特宣称“绝对没有”干预（日元）汇率。 新兴市场货币刷新日高，投资者关注贝森特汇率立场。",
          "url": "https://wallstreetcn.com/livenews/3045677",
          "source": "华尔街见闻-快讯",
          "ranks": [
            29
          ],
          "is_new": false,
          "appearance_count": 1,
          "time_info": "00时51分"
        }
      ]
    },
    {
      "keyword_group": "AI",
      "match_count": 7,
      "titles": [
        {
          "title": "如何看待马化腾罕见点评字节和阿里的 AI 策略？",
          "url": "https://www.zhihu.com/question/1999415789258826467",
          "source": "知乎",
          "ranks": [
            3
          ],
          "is_new": false,
          "appearance_count": 1,
          "time_info": "00时51分"
        },
        {
          "title": "史上最强业绩！SK海力士Q4营业利润翻倍至19.2万亿韩元 ，AI内存需求持续旺盛| 财报见闻",
          "url": "https://wallstreetcn.com/articles/3764353",
          "source": "华尔街见闻",
          "ranks": [
            8
          ],
          "is_new": false,
          "appearance_count": 1,
          "time_info": "00时51分"
        },
        {
          "title": "华尔街传奇大空头“剑指”数据中心：AI交易中最不该碰的领域！",
          "url": "https://www.cls.cn/detail/2272560",
          "source": "财联社热门",
          "ranks": [
            8
          ],
          "is_new": false,
          "appearance_count": 1,
          "time_info": "00时51分"
        },
        {
          "title": "赛道路演连轴转，听众不够用了？AI、太空、光伏谁在C位？",
          "url": "https://www.cls.cn/detail/2272316",
          "source": "财联社热门",
          "ranks": [
            9
          ],
          "is_new": false,
          "appearance_count": 1,
          "time_info": "00时51分"
        },
        {
          "title": "刘强东给老家建了间AI教室",
          "url": "https://news.ifeng.com/c/8qHvWO6SnwI",
          "source": "凤凰网",
          "ranks": [
            11
          ],
          "is_new": false,
          "appearance_count": 1,
          "time_info": "00时51分"
        },
        {
          "title": "马云谈AI时代教育",
          "url": "https://www.toutiao.com/trending/7600274916425351187/",
          "source": "今日头条",
          "ranks": [
            16
          ],
          "is_new": false,
          "appearance_count": 1,
          "time_info": "00时51分"
        },
        {
          "title": "AI将替代9200万工作岗位",
          "url": "https://www.baidu.com/s?wd=AI%E5%B0%86%E6%9B%BF%E4%BB%A39200%E4%B8%87%E5%B7%A5%E4%BD%9C%E5%B2%97%E4%BD%8D",
          "source": "百度热搜",
          "ranks": [
            17
          ],
          "is_new": false,
          "appearance_count": 1,
          "time_info": "00时51分"
        }
      ]
    },
    {
      "keyword_group": "指数",
      "match_count": 6,
      "titles": [
        {
          "title": "德国DAX 30指数初步收跌0.23%，报24836.90点。 法国股指初步收跌0.82%，意大利股指初步收跌0.52%、银行指数跌1.31%，英国股指初步收跌0.41%。",
          "url": "https://wallstreetcn.com/livenews/3045709",
          "source": "华尔街见闻-快讯",
          "ranks": [
            3
          ],
          "is_new": false,
          "appearance_count": 1,
          "time_info": "00时51分"
        },
        {
          "title": "欧洲STOXX 600指数初步收跌0.65%，报609.11点。 欧元区STOXX 50指数初步收跌0.81%，报5946.14点。 富时泛欧绩优300指数初步收跌0.73%，报2425.13点。",
          "url": "https://wallstreetcn.com/livenews/3045708",
          "source": "华尔街见闻-快讯",
          "ranks": [
            4
          ],
          "is_new": false,
          "appearance_count": 1,
          "time_info": "00时51分"
        },
        {
          "title": "标普500指数盘中转跌，较高位逾7000点回落至6978点。",
          "url": "https://flash.jin10.com/detail/20260129002458395800",
          "source": "金十数据",
          "ranks": [
            5
          ],
          "is_new": false,
          "appearance_count": 1,
          "time_info": "00时51分"
        },
        {
          "title": "希捷科技涨幅扩大至21%，创最近四年来最佳盘中表现。 西部数据涨幅重新扩大至10.56%，SanDisk涨幅重新扩大至8.4%，美光涨5.1%。 标普500指数转跌，三大股指目前整体上大致持平。",
          "url": "https://wallstreetcn.com/livenews/3045704",
          "source": "华尔街见闻-快讯",
          "ranks": [
            8
          ],
          "is_new": false,
          "appearance_count": 1,
          "time_info": "00时51分"
        },
        {
          "title": "【每日收评】三大指数震荡分化涨跌不一，全市场超3600股飘绿，黄金、油气等周期股持续爆发",
          "url": "https://www.cls.cn/detail/2272713",
          "source": "财联社热门",
          "ranks": [
            10
          ],
          "is_new": false,
          "appearance_count": 1,
          "time_info": "00时51分"
        },
        {
          "title": "非洲股市收盘播报｜周三（1月28日），南非富时/JSE非洲领先40可交易指数收涨1.49%，时隔一个交易日再创收盘历史新高，逼近11.75万点。",
          "url": "https://wallstreetcn.com/livenews/3045694",
          "source": "华尔街见闻-快讯",
          "ranks": [
            16
          ],
          "is_new": false,
          "appearance_count": 1,
          "time_info": "00时51分"
        }
      ]
    },
    {
      "keyword_group": "美股",
      "match_count": 3,
      "titles": [
        {
          "title": "美股“七巨头”财报即将亮相：投资者该关注哪些要点？",
          "url": "https://www.cls.cn/detail/2272925",
          "source": "财联社热门",
          "ranks": [
            4
          ],
          "is_new": false,
          "appearance_count": 1,
          "time_info": "00时51分"
        },
        {
          "title": "美股期指走高 美联储决议来袭 微软、Meta和特斯拉盘后公布财报 | 今夜看点",
          "url": "https://www.cls.cn/detail/2273158",
          "source": "财联社热门",
          "ranks": [
            11
          ],
          "is_new": false,
          "appearance_count": 1,
          "time_info": "00时51分"
        },
        {
          "title": "美股涨幅收窄，道指转跌，标普500指数持平，纳斯达克指数涨0.2%。",
          "url": "https://flash.jin10.com/detail/20260128235421935800",
          "source": "金十数据",
          "ranks": [
            29
          ],
          "is_new": false,
          "appearance_count": 1,
          "time_info": "00时51分"
        }
      ]
    },
    {
      "keyword_group": "价格",
      "match_count": 2,
      "titles": [
        {
          "title": "飞天茅台价格全线上涨",
          "url": "https://www.toutiao.com/trending/7599450620412166154/",
          "source": "今日头条",
          "ranks": [
            4
          ],
          "is_new": false,
          "appearance_count": 1,
          "time_info": "00时51分"
        },
        {
          "title": "黄金价格为何一路猛涨",
          "url": "https://search.bilibili.com/all?keyword=%E9%BB%84%E9%87%91%E4%BB%B7%E6%A0%BC%E4%B8%BA%E4%BD%95%E4%B8%80%E8%B7%AF%E7%8C%9B%E6%B6%A8",
          "source": "bilibili 热搜",
          "ranks": [
            21
          ],
          "is_new": false,
          "appearance_count": 1,
          "time_info": "00时51分"
        }
      ]
    }
  ],
  "report_image_url": "https://joyce677.github.io/TrendRadar/img/news.jpg"
}